setup.py
naagin/Binomialdistribution.py
naagin/Gaussiandistribution.py
naagin/Generaldistribution.py
naagin/__init__.py
naagin.egg-info/PKG-INFO
naagin.egg-info/SOURCES.txt
naagin.egg-info/dependency_links.txt
naagin.egg-info/not-zip-safe
naagin.egg-info/top_level.txt