Metadata-Version: 1.0
Name: naagin
Version: 0.1
Summary: Gaussian and Binomial distribution from Souvik Sankar Mitra
Home-page: UNKNOWN
Author: Souvik Sankar Mitra
Author-email: souviksankar2013@gmail.com
License: UNKNOWN
Platform: UNKNOWN
